freephil_docs/__init__.py
freephil_docs/markdown.py
freephil_docs/version.py
freephil_docs-0.1.1.dist-info/LICENSE
freephil_docs-0.1.1.dist-info/METADATA
freephil_docs-0.1.1.dist-info/WHEEL
freephil_docs-0.1.1.dist-info/top_level.txt
freephil_docs-0.1.1.dist-info/RECORD
