Metadata-Version: 2.1
Name: freephil-docs
Version: 0.1.1
Summary: Tool to create nice documentation of PHIL parameters
Author-email: Jan Stránský <jan.stransky@ibt.cas.cz>
License: GNU GPL 3
Keywords: phil,freephil
Classifier: Programming Language :: Python :: 3
Classifier: License :: OSI Approved :: GNU General Public License v3 or later (GPLv3+)
Classifier: Operating System :: OS Independent
Classifier: Topic :: Documentation
Requires-Python: >=3.9
License-File: LICENSE
Requires-Dist: freephil
